matprod.cpython-36m-i386-linux-gnu.so
matprod-1.0.dist-info/top_level.txt
matprod-1.0.dist-info/RECORD
matprod-1.0.dist-info/METADATA
matprod-1.0.dist-info/LICENSE
matprod-1.0.dist-info/WHEEL
