Metadata-Version: 2.1
Name: matprod
Version: 1.0
Summary: Fast repeated multiplication of 2x2 matrices in a compiled numpy extension
Home-page: https://github.com/electronsandstuff/MatProd
Author: Christopher M. Pierce
Author-email: contact@chris-pierce.com
License: GNU Affero General Public License v3 or later (AGPLv3+)
Platform: UNKNOWN
Classifier: Programming Language :: Python :: 3
Classifier: License :: OSI Approved :: GNU Affero General Public License v3 or later (AGPLv3+)
Classifier: Development Status :: 4 - Beta
Classifier: Operating System :: OS Independent
Requires-Python: >=3.1
Requires-Dist: numpy
